flashquiz/__init__.py
flashquiz/args.py
flashquiz/default.csv
flashquiz/quizzer.py
flashquiz/assets/card_back.jpg
flashquiz/assets/card_front.jpg
flashquiz/flashcards/__init__.py
flashquiz/flashcards/card.py
flashquiz/flashcards/deck.py
flashquiz/flashcards/parser.py
flashquiz/gui/__init__.py
flashquiz/gui/constants.py
flashquiz/gui/gui.py
flashquiz/gui/text.py
flashquiz-0.5.dist-info/LICENSE
flashquiz-0.5.dist-info/METADATA
flashquiz-0.5.dist-info/WHEEL
flashquiz-0.5.dist-info/entry_points.txt
flashquiz-0.5.dist-info/top_level.txt
flashquiz-0.5.dist-info/RECORD
