Metadata-Version: 2.1
Name: flashquiz
Version: 0.5
Summary: Practice your flashcards using python
Author: mike-fmh
Author-email: Michael MH <mikemh@uri.edu>
License: MIT
Project-URL: Source, https://github.com/mike-fmh/flashquiz
Project-URL: Homepage, https://mike-fmh.github.io/flashquiz/
Classifier: Programming Language :: Python :: 3
Classifier: License :: OSI Approved :: MIT License
Classifier: Operating System :: OS Independent
Requires-Python: >=3.8
License-File: LICENSE
Requires-Dist: pygame
Requires-Dist: argparse
